arthseg.abi3.so
arthseg-0.1.3.dist-info/METADATA
arthseg-0.1.3.dist-info/LICENSE
arthseg-0.1.3.dist-info/WHEEL
arthseg-0.1.3.dist-info/top_level.txt
arthseg-0.1.3.dist-info/RECORD
arthseg/__init__.pyi
