Metadata-Version: 2.1
Name: arthseg
Version: 0.1.3
Summary: Native library for arthropod segmentation
Home-page: https://github.com/matejpekar/arthseg
Author: Matej Pekar
Author-email: matej.pekar120@gmail.com
License: MIT
License-File: LICENSE
Requires-Dist: numpy
